msi_explorer/.pytest.ini
msi_explorer/__init__.py
msi_explorer/_analysis.py
msi_explorer/_database.py
msi_explorer/_maldi_ms_data.py
msi_explorer/_metadata.py
msi_explorer/_reader.py
msi_explorer/_selection.py
msi_explorer/_spectre_du_roi.py
msi_explorer/_true_mean_spec.py
msi_explorer/_widget.py
msi_explorer/_writer.py
msi_explorer/databases.conf
msi_explorer/hidden_databases.conf
msi_explorer/napari.yaml
msi_explorer/_tests/__init__.py
msi_explorer/_tests/test_maldi_ms_data.py
msi_explorer/_tests/test_metadata.py
msi_explorer/_tests/test_reader.py
msi_explorer/_tests/test_widget.py
msi_explorer/_tests/test_writer.py
msi_explorer/_tests/data/Example_Processed.ibd
msi_explorer/_tests/data/Example_Processed.imzML
msi_explorer/databases/Metabolite_database_ver1.csv
msi_explorer/databases/Metabolite_database_ver2.csv
msi_explorer/fonts/DejaVuSans.ttf
msi_explorer/ressources/logo.png
MSI_Explorer-1.0.1.dist-info/LICENSE
MSI_Explorer-1.0.1.dist-info/METADATA
MSI_Explorer-1.0.1.dist-info/WHEEL
MSI_Explorer-1.0.1.dist-info/entry_points.txt
MSI_Explorer-1.0.1.dist-info/top_level.txt
MSI_Explorer-1.0.1.dist-info/RECORD
