Metadata-Version: 2.1
Name: MSI-Explorer
Version: 1.0.1
Summary: a napari plug-in for biochemical annotation of mass spectrometry imaging data
Home-page: https://github.com/MMV-Lab/MSI-Explorer
Author: lennart kowitz
Author-email: lennart.kowitz@isas.de
License: BSD-3-Clause
Project-URL: Bug Tracker, https://github.com/MMV-Lab/MSI-Explorer/issues
Project-URL: Documentation, https://github.com/MMV-Lab/MSI-Explorer#README.md
Project-URL: Source Code, https://github.com/MMV-Lab/MSI-Explorer
Project-URL: User Support, https://github.com/MMV-Lab/MSI-Explorer/issues
Classifier: Development Status :: 2 - Pre-Alpha
Classifier: Framework :: napari
Classifier: Intended Audience :: Developers
Classifier: License :: OSI Approved :: BSD License
Classifier: Operating System :: OS Independent
Classifier: Programming Language :: Python
Classifier: Programming Language :: Python :: 3
Classifier: Programming Language :: Python :: 3 :: Only
Classifier: Programming Language :: Python :: 3.8
Classifier: Programming Language :: Python :: 3.9
Classifier: Programming Language :: Python :: 3.10
Classifier: Topic :: Scientific/Engineering :: Image Processing
Requires-Python: >=3.8
License-File: LICENSE
Requires-Dist: numpy
Requires-Dist: qtpy
Requires-Dist: pyimzml
Requires-Dist: matplotlib
Requires-Dist: vaex
Requires-Dist: opencv-python
Provides-Extra: testing
Requires-Dist: tox ; extra == 'testing'
Requires-Dist: pytest ; extra == 'testing'
Requires-Dist: pytest-cov ; extra == 'testing'
Requires-Dist: pytest-qt ; extra == 'testing'
Requires-Dist: napari ; extra == 'testing'
Requires-Dist: pyqt5 ; extra == 'testing'
